{"changeList":[{"Id":"ae48602a-b924-11ea-bb5d-1fb7b84ae166","ApiChange":"Enum type","ChangedApiName":"authenticatorAppContextType","ChangeType":"Addition","Description":"Added the **authenticatorAppContextType** enumeration type","Target":"authenticatorAppContextType"},{"Id":"ae4ac464-b924-11ea-bb5d-1fb7b84ae166","ApiChange":"Enum type","ChangedApiName":"externalEmailOtpState","ChangeType":"Addition","Description":"Added the **externalEmailOtpState** enumeration type","Target":"externalEmailOtpState"}],"Id":"ae45fcc0-b924-11ea-bb5d-1fb7b84ae166","CreatedBy":null,"Cloud":"prd","Version":"beta","CreatedDateTime":"2020-06-28T09:49:38.200Z","DocPRUrl":null,"WorkloadArea":""}